evasdk/Eva.py
evasdk/EvaDiscoverer.py
evasdk/__init__.py
evasdk/eva_errors.py
evasdk/eva_http_client.py
evasdk/eva_locker.py
evasdk/eva_ws.py
evasdk/helpers.py
evasdk/observer.py
evasdk/robot_state.py
evasdk/version.py
evasdk-5.0.1.dist-info/LICENSE
evasdk-5.0.1.dist-info/METADATA
evasdk-5.0.1.dist-info/WHEEL
evasdk-5.0.1.dist-info/top_level.txt
evasdk-5.0.1.dist-info/RECORD
