Metadata-Version: 2.1
Name: evasdk
Version: 5.0.1
Summary: SDK for the Automata Eva robotic arm
Home-page: https://github.com/automata-tech/eva_python_sdk
Author: Automata
Author-email: louis@automata.tech
License: Apache License 2.0
Platform: UNKNOWN
Classifier: Programming Language :: Python :: 3
Classifier: Development Status :: 4 - Beta
Classifier: Operating System :: OS Independent
Classifier: License :: OSI Approved :: Apache Software License
Requires-Python: >=3.6
License-File: LICENSE
Requires-Dist: requests
Requires-Dist: websocket-client
Requires-Dist: zeroconf
Requires-Dist: dataclasses
Requires-Dist: semver
